falko_horn/__init__.py
falko_horn/__main__.py
falko_horn/print_me_funcs.py
falko_horn-0.1.0.dist-info/licenses/LICENSE.txt
falko_horn-0.1.0.dist-info/METADATA
falko_horn-0.1.0.dist-info/WHEEL
falko_horn-0.1.0.dist-info/entry_points.txt
falko_horn-0.1.0.dist-info/top_level.txt
falko_horn-0.1.0.dist-info/RECORD
