Metadata-Version: 2.4
Name: falko_horn
Version: 0.1.0
Summary: My first package!
Author-email: Falko Horn <falko_horn@gmx.de>
Maintainer-email: Falko Horn <falko_horn@gmx.de>
License: Copyright 2025 Falko Horn
Project-URL: Homepage, https://github.com/DerParby/falko_horn
Project-URL: Documentation, https://github.com/DerParby/falko_horn/README.md
Keywords: Horn
Classifier: Programming Language :: Python :: 3.9
Classifier: Programming Language :: Python :: Implementation :: CPython
Classifier: License :: OSI Approved :: BSD License
Classifier: Intended Audience :: Developers
Classifier: Operating System :: POSIX :: Linux
Classifier: Operating System :: Microsoft :: Windows
Classifier: Operating System :: MacOS
Classifier: Operating System :: MacOS :: MacOS X
Requires-Python: >=3.9
License-File: LICENSE.txt
Dynamic: license-file
